msexpert/__init__.py
msexpert/annotation.py
msexpert/app.py
msexpert/cli.py
msexpert/constants.py
msexpert/gui.py
msexpert/ms_plot.py
msexpert/plotting.py
msexpert/utils.py
msexpert/__pycache__/__init__.cpython-38.pyc
msexpert-0.0.2.dist-info/LICENSE.txt
msexpert-0.0.2.dist-info/METADATA
msexpert-0.0.2.dist-info/WHEEL
msexpert-0.0.2.dist-info/entry_points.txt
msexpert-0.0.2.dist-info/top_level.txt
msexpert-0.0.2.dist-info/RECORD
