Metadata-Version: 2.1
Name: msexpert
Version: 0.0.2
Summary: An open-source Python package of the AlphaPept ecosystem
Home-page: https://github.com/MannLabs/msexpert
Author: Mann Labs
Author-email: opensource@alphapept.com
License: Apache
Project-URL: Mann Labs at MPIB, https://www.biochem.mpg.de/mann
Project-URL: Mann Labs at CPR, https://www.cpr.ku.dk/research/proteomics/mann/
Project-URL: GitHub, https://github.com/MannLabs/msexpert
Keywords: bioinformatics,software,AlphaPept ecosystem
Platform: UNKNOWN
Classifier: Development Status :: 1 - Planning
Classifier: Intended Audience :: Science/Research
Classifier: License :: OSI Approved :: Apache Software License
Classifier: Operating System :: OS Independent
Classifier: Programming Language :: Python :: 3
Classifier: Topic :: Scientific/Engineering :: Bio-Informatics
Requires-Python: >=3.8,<3.10
License-File: LICENSE.txt
Requires-Dist: click
Requires-Dist: streamlit
Requires-Dist: numba
Requires-Dist: numpy
Requires-Dist: matplotlib
Requires-Dist: pywin32 (==225) ; sys_platform == "win32"
Provides-Extra: development
Requires-Dist: jupyter ; extra == 'development'
Requires-Dist: jupyter-contrib-nbextensions ; extra == 'development'
Requires-Dist: pyinstaller ; extra == 'development'
Requires-Dist: autodocsumm ; extra == 'development'
Requires-Dist: sphinx-rtd-theme ; extra == 'development'
Requires-Dist: twine ; extra == 'development'
Requires-Dist: bumpversion ; extra == 'development'
Requires-Dist: pipdeptree ; extra == 'development'
Requires-Dist: ipykernel ; extra == 'development'
Requires-Dist: tqdm ; extra == 'development'
Requires-Dist: psutil ; extra == 'development'
Provides-Extra: development-stable
Requires-Dist: jupyter (==1.0.0) ; extra == 'development-stable'
Requires-Dist: jupyter-contrib-nbextensions (==0.5.1) ; extra == 'development-stable'
Requires-Dist: pyinstaller (==4.2) ; extra == 'development-stable'
Requires-Dist: autodocsumm (==0.2.6) ; extra == 'development-stable'
Requires-Dist: sphinx-rtd-theme (==0.5.2) ; extra == 'development-stable'
Requires-Dist: twine (==3.4.1) ; extra == 'development-stable'
Requires-Dist: bumpversion (==0.6.0) ; extra == 'development-stable'
Requires-Dist: pipdeptree (==2.1.0) ; extra == 'development-stable'
Requires-Dist: ipykernel (==6.4.0) ; extra == 'development-stable'
Requires-Dist: tqdm (==4.61.1) ; extra == 'development-stable'
Requires-Dist: psutil (==5.8.0) ; extra == 'development-stable'
Provides-Extra: stable
Requires-Dist: click (==7.1.2) ; extra == 'stable'
Requires-Dist: streamlit (==1.0.0) ; extra == 'stable'
Requires-Dist: numba ; extra == 'stable'
Requires-Dist: numpy ; extra == 'stable'
Requires-Dist: matplotlib ; extra == 'stable'
